controller.v
`timescale 1ns/1ns
// IR must have load signal 
module Controller(input [7:0] inst, input clk, zero, output reg pc_src, ld_pc, mem_adr_src, mem_write,
 stack_src, tos, stack_push, stack_pop, ld_B, output reg [1:0] alu_op);

  localparam[3:0] inst_fetch = 0, inst_decode = 1,
    and_sub_add_1 = 2, and_sub_add_2 = 3, and_sub_add_3 = 4,  //3 -> NOT
    push_1 = 5, push_2 = 6,     
    pop_1 = 7, pop_2 = 8,
    jmp = 9,
    jz_1 = 10, jz_2 = 11;
    
  reg[3:0] ps = inst_fetch, ns = inst_fetch; 
   
  always @(ps) begin 
    pc_src <= 0; ld_pc <= 0; mem_adr_src <= 0; mem_write <= 0; stack_src <= 0; tos <= 0; 
    stack_push <= 0; stack_pop <= 0; ld_B <= 0; alu_op <= 2'b00;
    
    case(ps)
      inst_fetch: begin
        ns <= inst_decode;
        mem_adr_src <= 1;
        ld_pc <= 1;
      end 
      inst_decode: begin
        case(inst[7:5])
          3'b000: ns <= and_sub_add_1; //add
          3'b001: ns <= and_sub_add_1; //sub 
          3'b010: ns <= and_sub_add_1; //and
          3'b011: ns <= and_sub_add_2; //not
          3'b100: ns <= push_1; //push
          3'b101: ns <= pop_1; //pop
          3'b110: ns <= jmp; //jmp
          3'b111: ns <= jz_1; //jmp zero
        endcase
      end
      and_sub_add_1: begin
        ns <= and_sub_add_2;
        tos <= 1;
        stack_pop <= 1;
        ld_B <= 1;
      end
      and_sub_add_2: begin
        ns <= and_sub_add_3;
        alu_op <= inst[7:6];
        tos <= 1;
        stack_pop <= 1;
      end
      and_sub_add_3: begin
        ns <= inst_fetch;
        stack_src <= 1;
        stack_push <= 1;
      end
      push_1: begin
        ns <= push_2;
      end
      push_2: begin
        ns <= inst_fetch;
        stack_push <= 1;
        stack_src <= 1;
      end
      pop_1: begin
        ns <= pop_2;
        stack_pop <= 1;
        tos <= 1;
      end
      pop_2: begin
        ns <= inst_fetch;
        mem_write <= 1;
      end
      jmp: begin 
        ns <= inst_fetch;
        ld_pc <= 1;
        pc_src <= 1;
      end
      jz_1: begin 
        ns <= zero ? jz_2 : inst_fetch;
        tos <= 1;
      end
      jz_2: begin 
        ns <= inst_fetch;
        ld_pc <= 1;
        pc_src <= 1;
      end        
    endcase
  end
  
  always@ (posedge clk) begin 
    $display("%b", inst);
    if (inst == 8'b11111111)
      $finish;
    ps <= ns;
  end 
endmodule

alu.v
`timescale 1ns/1ns

module ALU(input signed [7:0] A, input signed [7:0] B, input [1:0] alu_op, output reg [7:0] R);

  always @(A, B, alu_op) begin
    case(alu_op)
      2'b00: R = A + B;
      2'b01: R = A - B;
      2'b10: R = A & B;
      2'b11: R = ~A;
    endcase
  end
endmodule

stack.v
`timescale 1ns/1ns
module Stack(input push_sig, pop_sig, tos_sig, clk, input[7:0] push_data ,output reg [7:0] out_data);
  
  reg[11:0] data[7:0];
  reg[3:0] stack_pointer = 4'b0;
  
  always @(tos_sig) begin
    out_data = data[stack_pointer - 1];
  end
  
  always @(posedge clk, push_sig, tos_sig, pop_sig, push_data) begin
    if(push_sig) begin
      data[stack_pointer] <= push_data;
      stack_pointer <= stack_pointer + 1;
    end
    if(pop_sig) begin
      stack_pointer = stack_pointer - 1;
    end
  end

  integer i;
  initial begin
    for(i = 0; i < 8; i = i + 1) begin: loop2
      $dumpvars(0, data[i]);
    end
  end
  
endmodule

data_memory.v
`timescale 1ns/1ns
module DataMemory(input[4:0] address, input[7:0] write_data, input mem_write_sig, clk, output reg[7:0] read_data);

  reg[7:0] data[31:0];

  initial begin
    //data[15] = 8'b10101010;
    //data[16] = 8'b00000001;
    //data[17] = 8'b00000010;
    $readmemb("instructions.mips", data);
  end

  always @(posedge clk) begin
    if(mem_write_sig & clk)
      data[address] <= write_data;
  end

  always @(address) begin
    read_data = data[address];
  end

  integer i;
  initial begin
    for(i = 0; i < 20; i = i + 1) begin: loop
      $dumpvars(0, data[i]);
    end
  end

endmodule

data_path.v
`timescale 1ns/1ns
module DataPath(input clk, ld_pc, ld_B, stack_src, mem_write_sig, push_sig, pop_sig, tos_sig, pc_src,  input[1:0] alu_op, output reg z, output reg[7:0] instruction);
  
  reg[4:0] pc;
  reg[7:0] mdr;
  reg[7:0] B_reg;
  reg[7:0] alu_out_reg;

  wire[7:0] data_memory_out;
  wire[7:0] stack_out;
  wire[7:0] alu_out;

  initial begin
    pc = 4'b0;
  end

  always @(posedge clk) begin
    if(ld_pc) pc <= (pc_src == 1'b0 ? pc + 1 : instruction[4:0]);
    if(ld_B) B_reg <= stack_out;
  
    mdr <= data_memory_out;
    instruction <= data_memory_out;
    z <= (stack_out == 0);
    alu_out_reg <= alu_out;    
  end

  DataMemory data_memory(pc, stack_out, mem_write_sig, clk, data_memory_out);
  Stack stack(push_sig, pop_sig, tos_sig, clk, ((stack_src == 1'b0) ? mdr : alu_out_reg), stack_out);
  ALU alu(B_reg, stack_out, alu_op, alu_out); 
   
endmodule

CPU.v
`timescale 1ns/1ns
module CPU(input clk);
  wire z;
  wire[7:0] inst;
  wire pc_src, ld_pc, mem_adr_src, mem_write_sig, stack_src, tos_sig, push_sig, pop_sig, ld_B;
  wire[1:0] alu_op;

  
  DataPath data_path(clk, ld_pc, ld_B, stack_src, mem_write_sig, push_sig, pop_sig, tos_sig, pc_src, alu_op, z, inst);
  Controller controller(inst, clk, z, pc_src, ld_pc, mem_adr_src, mem_write_sig, stack_src, tos_sig, push_sig, pop_sig, ld_B, alu_op);

endmodule

CPU_test.v
`timescale 1ns/1ns

module CPUTest;
  reg clk = 1;

  CPU cpu(clk);
  initial begin
    clk = 1;
  end
  always begin
    #20 clk = ~clk;
    //if(clk == 1) begin
      //$display("");
      //$display("-------------------------------------------------------");
      //$display("a clock pulse passed!");
      //$display("-------------------------------------------------------");
      //$display("");
    //end
  end

  initial begin
    $dumpfile("cpu.vcd");
    $dumpvars(0, CPUTest);
  end
endmodule

dump.vcd
$date
	Tue May 26 17:56:58 2015
$end
$version
	Icarus Verilog
$end
$timescale
	1ns
$end
$scope module CPUTest $end
$scope module cpu $end
$scope module data_path $end
$scope module data_memory $end
$var reg 8 ! \data[0] [7:0] $end
$upscope $end
$upscope $end
$upscope $end
$upscope $end
$scope module CPUTest $end
$scope module cpu $end
$scope module data_path $end
$scope module data_memory $end
$var reg 8 " \data[1] [7:0] $end
$upscope $end
$upscope $end
$upscope $end
$upscope $end
$scope module CPUTest $end
$scope module cpu $end
$scope module data_path $end
$scope module data_memory $end
$var reg 8 # \data[2] [7:0] $end
$upscope $end
$upscope $end
$upscope $end
$upscope $end
$scope module CPUTest $end
$scope module cpu $end
$scope module data_path $end
$scope module data_memory $end
$var reg 8 $ \data[3] [7:0] $end
$upscope $end
$upscope $end
$upscope $end
$upscope $end
$scope module CPUTest $end
$scope module cpu $end
$scope module data_path $end
$scope module data_memory $end
$var reg 8 % \data[4] [7:0] $end
$upscope $end
$upscope $end
$upscope $end
$upscope $end
$scope module CPUTest $end
$scope module cpu $end
$scope module data_path $end
$scope module data_memory $end
$var reg 8 & \data[5] [7:0] $end
$upscope $end
$upscope $end
$upscope $end
$upscope $end
$scope module CPUTest $end
$scope module cpu $end
$scope module data_path $end
$scope module data_memory $end
$var reg 8 ' \data[6] [7:0] $end
$upscope $end
$upscope $end
$upscope $end
$upscope $end
$scope module CPUTest $end
$scope module cpu $end
$scope module data_path $end
$scope module data_memory $end
$var reg 8 ( \data[7] [7:0] $end
$upscope $end
$upscope $end
$upscope $end
$upscope $end
$scope module CPUTest $end
$scope module cpu $end
$scope module data_path $end
$scope module data_memory $end
$var reg 8 ) \data[8] [7:0] $end
$upscope $end
$upscope $end
$upscope $end
$upscope $end
$scope module CPUTest $end
$scope module cpu $end
$scope module data_path $end
$scope module data_memory $end
$var reg 8 * \data[9] [7:0] $end
$upscope $end
$upscope $end
$upscope $end
$upscope $end
$scope module CPUTest $end
$scope module cpu $end
$scope module data_path $end
$scope module data_memory $end
$var reg 8 + \data[10] [7:0] $end
$upscope $end
$upscope $end
$upscope $end
$upscope $end
$scope module CPUTest $end
$scope module cpu $end
$scope module data_path $end
$scope module data_memory $end
$var reg 8 , \data[11] [7:0] $end
$upscope $end
$upscope $end
$upscope $end
$upscope $end
$scope module CPUTest $end
$scope module cpu $end
$scope module data_path $end
$scope module data_memory $end
$var reg 8 - \data[12] [7:0] $end
$upscope $end
$upscope $end
$upscope $end
$upscope $end
$scope module CPUTest $end
$scope module cpu $end
$scope module data_path $end
$scope module data_memory $end
$var reg 8 . \data[13] [7:0] $end
$upscope $end
$upscope $end
$upscope $end
$upscope $end
$scope module CPUTest $end
$scope module cpu $end
$scope module data_path $end
$scope module data_memory $end
$var reg 8 / \data[14] [7:0] $end
$upscope $end
$upscope $end
$upscope $end
$upscope $end
$scope module CPUTest $end
$scope module cpu $end
$scope module data_path $end
$scope module data_memory $end
$var reg 8 0 \data[15] [7:0] $end
$upscope $end
$upscope $end
$upscope $end
$upscope $end
$scope module CPUTest $end
$scope module cpu $end
$scope module data_path $end
$scope module data_memory $end
$var reg 8 1 \data[16] [7:0] $end
$upscope $end
$upscope $end
$upscope $end
$upscope $end
$scope module CPUTest $end
$scope module cpu $end
$scope module data_path $end
$scope module data_memory $end
$var reg 8 2 \data[17] [7:0] $end
$upscope $end
$upscope $end
$upscope $end
$upscope $end
$scope module CPUTest $end
$scope module cpu $end
$scope module data_path $end
$scope module data_memory $end
$var reg 8 3 \data[18] [7:0] $end
$upscope $end
$upscope $end
$upscope $end
$upscope $end
$scope module CPUTest $end
$scope module cpu $end
$scope module data_path $end
$scope module data_memory $end
$var reg 8 4 \data[19] [7:0] $end
$upscope $end
$upscope $end
$upscope $end
$upscope $end
$scope module CPUTest $end
$scope module cpu $end
$scope module data_path $end
$scope module stack $end
$var reg 12 5 \data[0] [11:0] $end
$upscope $end
$upscope $end
$upscope $end
$upscope $end
$scope module CPUTest $end
$scope module cpu $end
$scope module data_path $end
$scope module stack $end
$var reg 12 6 \data[1] [11:0] $end
$upscope $end
$upscope $end
$upscope $end
$upscope $end
$scope module CPUTest $end
$scope module cpu $end
$scope module data_path $end
$scope module stack $end
$var reg 12 7 \data[2] [11:0] $end
$upscope $end
$upscope $end
$upscope $end
$upscope $end
$scope module CPUTest $end
$scope module cpu $end
$scope module data_path $end
$scope module stack $end
$var reg 12 8 \data[3] [11:0] $end
$upscope $end
$upscope $end
$upscope $end
$upscope $end
$scope module CPUTest $end
$scope module cpu $end
$scope module data_path $end
$scope module stack $end
$var reg 12 9 \data[4] [11:0] $end
$upscope $end
$upscope $end
$upscope $end
$upscope $end
$scope module CPUTest $end
$scope module cpu $end
$scope module data_path $end
$scope module stack $end
$var reg 12 : \data[5] [11:0] $end
$upscope $end
$upscope $end
$upscope $end
$upscope $end
$scope module CPUTest $end
$scope module cpu $end
$scope module data_path $end
$scope module stack $end
$var reg 12 ; \data[6] [11:0] $end
$upscope $end
$upscope $end
$upscope $end
$upscope $end
$scope module CPUTest $end
$scope module cpu $end
$scope module data_path $end
$scope module stack $end
$var reg 12 < \data[7] [11:0] $end
$upscope $end
$upscope $end
$upscope $end
$upscope $end
$scope module CPUTest $end
$var reg 1 = clk $end
$scope module cpu $end
$var wire 2 > alu_op [1:0] $end
$var wire 1 ? clk $end
$var wire 8 @ inst [7:0] $end
$var wire 1 A ld_B $end
$var wire 1 B ld_pc $end
$var wire 1 C mem_adr_src $end
$var wire 1 D mem_write_sig $end
$var wire 1 E pc_src $end
$var wire 1 F pop_sig $end
$var wire 1 G push_sig $end
$var wire 1 H stack_src $end
$var wire 1 I tos_sig $end
$var wire 1 J z $end
$scope module data_path $end
$var wire 2 K alu_op [1:0] $end
$var wire 8 L alu_out [7:0] $end
$var wire 1 ? clk $end
$var wire 8 M data_memory_out [7:0] $end
$var wire 1 A ld_B $end
$var wire 1 B ld_pc $end
$var wire 1 D mem_write_sig $end
$var wire 1 E pc_src $end
$var wire 1 F pop_sig $end
$var wire 1 G push_sig $end
$var wire 8 N stack_out [7:0] $end
$var wire 1 H stack_src $end
$var wire 1 I tos_sig $end
$var reg 8 O B_reg [7:0] $end
$var reg 8 P alu_out_reg [7:0] $end
$var reg 8 Q instruction [7:0] $end
$var reg 8 R mdr [7:0] $end
$var reg 5 S pc [4:0] $end
$var reg 1 T z $end
$scope module data_memory $end
$var wire 5 U address [4:0] $end
$var wire 1 ? clk $end
$var wire 1 D mem_write_sig $end
$var wire 8 V write_data [7:0] $end
$var integer 32 W i [31:0] $end
$var reg 8 X read_data [7:0] $end
$scope begin loop $end
$upscope $end
$upscope $end
$scope module stack $end
$var wire 1 ? clk $end
$var wire 1 F pop_sig $end
$var wire 8 Y push_data [7:0] $end
$var wire 1 G push_sig $end
$var wire 1 I tos_sig $end
$var integer 32 Z i [31:0] $end
$var reg 8 [ out_data [7:0] $end
$var reg 4 \ stack_pointer [3:0] $end
$scope begin loop2 $end
$upscope $end
$upscope $end
$scope module alu $end
$var wire 8 ] A [7:0] $end
$var wire 8 ^ B [7:0] $end
$var wire 2 _ alu_op [1:0] $end
$var reg 8 ` R [7:0] $end
$upscope $end
$upscope $end
$scope module controller $end
$var wire 1 ? clk $end
$var wire 8 a inst [7:0] $end
$var wire 1 J zero $end
$var reg 2 b alu_op [1:0] $end
$var reg 1 c ld_B $end
$var reg 1 d ld_pc $end
$var reg 1 e mem_adr_src $end
$var reg 1 f mem_write $end
$var reg 4 g ns [3:0] $end
$var reg 1 h pc_src $end
$var reg 4 i ps [3:0] $end
$var reg 1 j stack_pop $end
$var reg 1 k stack_push $end
$var reg 1 l stack_src $end
$var reg 1 m tos $end
$upscope $end
$upscope $end
$upscope $end
$enddefinitions $end
#0
$dumpvars
0m
0l
0k
0j
b0 i
0h
b1 g
0f
1e
1d
0c
b0 b
b10001111 a
bx `
b0 _
bx ^
bx ]
b0 \
bx [
b1000 Z
b10001111 Y
b10001111 X
b10100 W
bx V
b0 U
xT
b0 S
b10001111 R
b10001111 Q
bx P
bx O
bx N
b10001111 M
bx L
b0 K
xJ
0I
0H
0G
0F
0E
0D
1C
1B
0A
b10001111 @
1?
b0 >
1=
bx <
bx ;
bx :
bx 9
bx 8
bx 7
bx 6
bx 5
bx 4
bx 3
bx 2
bx 1
bx 0
bx /
bx .
bx -
bx ,
bx +
bx *
bx )
bx (
bx '
b11111111 &
b0 %
b0 $
b10010001 #
b10010000 "
b10001111 !
$end
#20
0=
0?
#40
b101 g
0e
0C
0d
0B
b10010000 X
b10010000 M
b1 i
b1 S
b1 U
1=
1?
#60
0=
0?
#80
b110 g
b10010000 Y
b10010000 Q
b10010000 @
b10010000 a
b10010000 R
b101 i
1=
1?
#100
0=
0?
#120
b1 \
b0xxxxxxxx 5
bx Y
1l
1H
1k
1G
b0 g
b110 i
1=
1?
#140
0=
0?
#160
b10010000 Y
1d
1B
1e
1C
b1 g
0k
0G
0l
0H
b0 i
b10 \
b0xxxxxxxx 6
1=
1?
#180
0=
0?
#200
b101 g
0e
0C
0d
0B
b10010001 X
b10010001 M
b1 i
b10 S
b10 U
1=
1?
#220
0=
0?
#240
b110 g
b10010001 Y
b10010001 Q
b10010001 @
b10010001 a
b10010001 R
b101 i
1=
1?
#260
0=
0?
#280
b11 \
b0xxxxxxxx 7
bx Y
1l
1H
1k
1G
b0 g
b110 i
1=
1?
#300
0=
0?
#320
b10010001 Y
1d
1B
1e
1C
b1 g
0k
0G
0l
0H
b0 i
b100 \
b0xxxxxxxx 8
1=
1?
#340
0=
0?
#360
b101 g
0e
0C
0d
0B
b0 X
b0 M
b1 i
b11 S
b11 U
1=
1?
#380
0=
0?
#400
b110 g
b0 Y
b0 Q
b0 @
b0 a
b0 R
b101 i
1=
1?
#420
0=
0?
#440
b101 \
b0xxxxxxxx 9
bx Y
1l
1H
1k
1G
b0 g
b110 i
1=
1?
#460
0=
0?
#480
b0 Y
1d
1B
1e
1C
b1 g
0k
0G
0l
0H
b0 i
b110 \
b0xxxxxxxx :
1=
1?
#500
0=
0?
#520
b10 g
0e
0C
0d
0B
b1 i
b100 S
b100 U
1=
1?
#540
0=
0?
#560
b101 \
1c
1A
1j
1F
1m
1I
b11 g
b10 i
1=
1?
#580
0=
0?
#600
b100 g
0c
0A
1j
1F
1m
1I
b11 i
b11 \
1=
1?
#620
0=
0?
#640
b0xxxxxxxx 7
bx Y
1k
1G
1l
1H
b0 g
0j
0F
0m
0I
b100 i
b11 \
1=
1?
#660
0=
0?
#680
b0 Y
1d
1B
1e
1C
b1 g
0k
0G
0l
0H
b0 i
b100 \
b0xxxxxxxx 8
1=
1?
#700
0=
0?
#720
b10 g
0e
0C
0d
0B
b11111111 X
b11111111 M
b101 S
b101 U
b1 i
1=
1?
#740
0=
0?
#760
b11 \
1c
1A
1j
1F
1m
1I
b11 g
b11111111 Y
b10 i
b11111111 Q
b11111111 @
b11111111 a
b11111111 R
1=
1?
#780
0=
0?
#800
b10 \
1=
1?
