controller.v
`timescale 1ns/1ns
// IR must have load signal 
module Controller(input [7:0] inst, input clk, zero, output reg pc_src, ld_pc, ld_MDR, mem_adr_src, mem_write,
 stack_src, tos, stack_push, stack_pop, ld_B, ld_IR, output reg [1:0] alu_op);

  localparam[3:0] init = -1, inst_fetch = 0, inst_decode = 1,
    and_sub_add_1 = 2, and_sub_add_2 = 3, and_sub_add_3 = 4,  //3 -> NOT
    push_1 = 5, push_2 = 6,     
    pop_1 = 7, pop_2 = 8,
    jmp = 9,
    jz_1 = 10, jz_2 = 11;
  
  reg[3:0] ps = init, ns = inst_fetch; 
  
  always @(ps) begin 
    pc_src <= 0; ld_pc <= 0; mem_adr_src <= 0; mem_write <= 0; stack_src <= 0; tos <= 0; 
    stack_push <= 0; stack_pop <= 0; ld_B <= 0; ld_IR <= 0; alu_op <= 2'b00;
    ld_MDR <= 0;

    case(ps)
      init: ns <= inst_fetch;

      inst_fetch: begin
        ns <= inst_decode;
        mem_adr_src <= 1;
        ld_IR <= 1;
        ld_pc <= 1;
      end 
      inst_decode: begin
        //ld_IR <= 1;
        case(inst[7:5])
          3'b000: begin
            ns <= and_sub_add_1; //add
            stack_pop <= 1;
            ld_B <= 1;
          end
          3'b001: begin
            ns <= and_sub_add_1; //sub 
            stack_pop <= 1;
            ld_B <= 1;
          end
          3'b010: begin
            ns <= and_sub_add_1; //and
            stack_pop <= 1;
            ld_B <= 1;
          end
          3'b011: begin
            ns <= and_sub_add_2; //not
            stack_pop <= 1;
            ld_B <= 1;
          end 
          3'b100: begin
            ns <= push_1; //push
            ld_MDR <= 1;
          end
          3'b101: begin
            ns <= pop_1; //pop
            stack_pop <= 1;
          end
          3'b110: ns <= jmp; //jmp
          3'b111: ns <= jz_1; //jmp zero
        endcase
      end
      and_sub_add_1: begin
        ns <= and_sub_add_2;
        tos <= 1;
        stack_pop <= 1;
        //ld_B <= 1;
      end
      and_sub_add_2: begin
        //ns <= and_sub_add_3;
        ns <= inst_fetch;
        alu_op <= inst[7:6];
        tos <= 1;
        //stack_pop <= 1;
        //new:
        stack_push <= 1;
        stack_src <= 1;
      end
      and_sub_add_3: begin
        ns <= inst_fetch;
        stack_src <= 1;
        //stack_push <= 1;
      end
      push_1: begin
        ns <= push_2;
        //ld_MDR <= 1;
        stack_push <= 1;
      end
      push_2: begin
        ns <= inst_fetch;
        //stack_push <= 1;
        stack_src <= 0;
        //stack_src <= 1;
      end
      pop_1: begin
        ns <= inst_fetch; //pop_2;
        tos <= 1;
        mem_write <= 1;
      end
/*      pop_2: begin
        ns <= inst_fetch;
        mem_write <= 1;
      end */
      jmp: begin 
        ns <= inst_fetch;
        ld_pc <= 1;
        pc_src <= 1;
      end
      jz_1: begin 
        ns <= zero ? jz_2 : inst_fetch;
        tos <= 1;
      end
      jz_2: begin 
        ns <= inst_fetch;
        ld_pc <= 1;
        pc_src <= 1;
      end        
    endcase
  end
  
  always@ (posedge clk) begin 
    $display("%b", inst);
    if (inst == 8'b11111111)
      $finish;
    ps <= ns;
  end 
endmodule

alu.v
`timescale 1ns/1ns

module ALU(input signed [7:0] A, input signed [7:0] B, input [1:0] alu_op, output reg [7:0] R);

  always @(A, B, alu_op) begin
    case(alu_op)
      2'b00: R = A + B;
      2'b01: R = A - B;
      2'b10: R = A & B;
      2'b11: R = ~A;
    endcase
  end
endmodule

stack.v
`timescale 1ns/1ns
module Stack(input push_sig, pop_sig, tos_sig, clk, input[7:0] push_data ,output reg [7:0] out_data);
  
  reg[7:0] data[11:0];
  reg[2:0] stack_pointer = 3'b0;
  
//  always @(tos_sig) begin
//  end

/*  always @(stack_pointer) begin
    if(tos_sig) begin
      out_data = data[stack_pointer - 1];
    end
  end */
 
//  always @(posedge clk) begin
//    out_data <= data[stack_pointer-1];
//  end
  //push
  always @(posedge clk) begin
    if(push_sig) begin
      data[stack_pointer] = push_data;
      stack_pointer = stack_pointer + 1;
    end
  end

  //pop
  always @(posedge clk) begin
    if(pop_sig) begin
      out_data = data[stack_pointer - 1];
      stack_pointer = stack_pointer - 1;
    end
    else begin
      out_data = data[stack_pointer - 1];
    end
  end
 
  /*always @(posedge clk, push_sig, tos_sig, pop_sig, push_data) begin
    if(push_sig) begin
      data[stack_pointer] = push_data;
      stack_pointer = stack_pointer + 1;
    end
    if(pop_sig) begin
      stack_pointer = stack_pointer - 1;
    end
  end */

  integer i;
  initial begin
    for(i = 0; i < 12; i = i + 1) begin: loop2
      $dumpvars(0, data[i]);
    end
  end
  
endmodule

data_memory.v
`timescale 1ns/1ns
module DataMemory(input[4:0] address, input[7:0] write_data, input mem_write_sig, clk, output reg[7:0] read_data);

  reg[7:0] data[31:0];

  initial begin
    data[15] = 8'b10101010;
    data[16] = 8'b00000001;
    data[17] = 8'b00000010;
    $readmemb("instructions.mips", data);
  end

  always @(posedge clk) begin
    if(mem_write_sig) begin
      $display("FUCK!");
      $display("%b",write_data);
      data[address] <= write_data;
    end
  end

  always @(address) begin
    read_data = data[address];
  end

  integer i;
  initial begin
    for(i = 0; i < 20; i = i + 1) begin: loop
      $dumpvars(0, data[i]);
    end
  end

endmodule

data_path.v
`timescale 1ns/1ns
module DataPath(input clk, ld_pc, ld_B, ld_IR, ld_MDR, stack_src, mem_write_sig, push_sig, pop_sig, tos_sig, pc_src,  input[1:0] alu_op, input mem_adr_src, output reg z, output reg[7:0] instruction);
  
  reg[4:0] pc;
  reg[7:0] mdr;
  reg[7:0] B_reg;
  reg[7:0] alu_out_reg;

  wire[7:0] data_memory_out;
  wire[7:0] stack_out;
  wire[7:0] alu_out;

  initial begin
    pc = 4'b0;
  end

  always @(posedge clk) begin
    if(ld_pc) pc <= (pc_src == 1'b0 ? pc + 1 : instruction[4:0]);
    if(ld_B) B_reg <= stack_out;
    if(ld_MDR) mdr <= data_memory_out;
    if (ld_IR == 1'b1) instruction <= data_memory_out;
    z <= (stack_out == 0);
    alu_out_reg <= alu_out;    
  end

  DataMemory data_memory((mem_adr_src ? pc : instruction[4:0]), stack_out, mem_write_sig, clk, data_memory_out);

  //CHANGE: changed alu_out_reg to alu_out
  Stack stack(push_sig, pop_sig, tos_sig, clk, ((stack_src == 1'b0) ? mdr : alu_out), stack_out);
  ALU alu(B_reg, stack_out, alu_op, alu_out); 
   
endmodule

CPU.v
`timescale 1ns/1ns
module CPU(input clk);
  wire z;
  wire[7:0] inst;
  wire pc_src, ld_pc, mem_adr_src, mem_write_sig, stack_src, tos_sig, push_sig, pop_sig, ld_B, ld_IR, ld_MDR;
  wire[1:0] alu_op;

  
  DataPath data_path(clk, ld_pc, ld_B, ld_IR, ld_MDR, stack_src, mem_write_sig, push_sig, pop_sig, tos_sig, pc_src, alu_op, mem_adr_src, z, inst);
  Controller controller(inst, clk, z, pc_src, ld_pc, ld_MDR, mem_adr_src, mem_write_sig, stack_src, tos_sig, push_sig, pop_sig, ld_B, ld_IR, alu_op);

endmodule

CPU_test.v
`timescale 1ns/1ns

module CPUTest;
  reg clk = 0;

  CPU cpu(clk);
  initial begin
    clk = 0;
  end
  always begin
    #20 clk = ~clk;
    //if(clk == 1) begin
      //$display("");
      //$display("-------------------------------------------------------");
      //$display("a clock pulse passed!");
      //$display("-------------------------------------------------------");
      //$display("");
    //end
  end

  initial begin
    $dumpfile("cpu.vcd");
    $dumpvars(0, CPUTest);
  end
endmodule

dump.vcd
$date
	Thu May 28 21:23:38 2015
$end
$version
	Icarus Verilog
$end
$timescale
	1ns
$end
$scope module CPUTest $end
$scope module cpu $end
$scope module data_path $end
$scope module data_memory $end
$var reg 8 ! \data[0] [7:0] $end
$upscope $end
$upscope $end
$upscope $end
$upscope $end
$scope module CPUTest $end
$scope module cpu $end
$scope module data_path $end
$scope module data_memory $end
$var reg 8 " \data[1] [7:0] $end
$upscope $end
$upscope $end
$upscope $end
$upscope $end
$scope module CPUTest $end
$scope module cpu $end
$scope module data_path $end
$scope module data_memory $end
$var reg 8 # \data[2] [7:0] $end
$upscope $end
$upscope $end
$upscope $end
$upscope $end
$scope module CPUTest $end
$scope module cpu $end
$scope module data_path $end
$scope module data_memory $end
$var reg 8 $ \data[3] [7:0] $end
$upscope $end
$upscope $end
$upscope $end
$upscope $end
$scope module CPUTest $end
$scope module cpu $end
$scope module data_path $end
$scope module data_memory $end
$var reg 8 % \data[4] [7:0] $end
$upscope $end
$upscope $end
$upscope $end
$upscope $end
$scope module CPUTest $end
$scope module cpu $end
$scope module data_path $end
$scope module data_memory $end
$var reg 8 & \data[5] [7:0] $end
$upscope $end
$upscope $end
$upscope $end
$upscope $end
$scope module CPUTest $end
$scope module cpu $end
$scope module data_path $end
$scope module data_memory $end
$var reg 8 ' \data[6] [7:0] $end
$upscope $end
$upscope $end
$upscope $end
$upscope $end
$scope module CPUTest $end
$scope module cpu $end
$scope module data_path $end
$scope module data_memory $end
$var reg 8 ( \data[7] [7:0] $end
$upscope $end
$upscope $end
$upscope $end
$upscope $end
$scope module CPUTest $end
$scope module cpu $end
$scope module data_path $end
$scope module data_memory $end
$var reg 8 ) \data[8] [7:0] $end
$upscope $end
$upscope $end
$upscope $end
$upscope $end
$scope module CPUTest $end
$scope module cpu $end
$scope module data_path $end
$scope module data_memory $end
$var reg 8 * \data[9] [7:0] $end
$upscope $end
$upscope $end
$upscope $end
$upscope $end
$scope module CPUTest $end
$scope module cpu $end
$scope module data_path $end
$scope module data_memory $end
$var reg 8 + \data[10] [7:0] $end
$upscope $end
$upscope $end
$upscope $end
$upscope $end
$scope module CPUTest $end
$scope module cpu $end
$scope module data_path $end
$scope module data_memory $end
$var reg 8 , \data[11] [7:0] $end
$upscope $end
$upscope $end
$upscope $end
$upscope $end
$scope module CPUTest $end
$scope module cpu $end
$scope module data_path $end
$scope module data_memory $end
$var reg 8 - \data[12] [7:0] $end
$upscope $end
$upscope $end
$upscope $end
$upscope $end
$scope module CPUTest $end
$scope module cpu $end
$scope module data_path $end
$scope module data_memory $end
$var reg 8 . \data[13] [7:0] $end
$upscope $end
$upscope $end
$upscope $end
$upscope $end
$scope module CPUTest $end
$scope module cpu $end
$scope module data_path $end
$scope module data_memory $end
$var reg 8 / \data[14] [7:0] $end
$upscope $end
$upscope $end
$upscope $end
$upscope $end
$scope module CPUTest $end
$scope module cpu $end
$scope module data_path $end
$scope module data_memory $end
$var reg 8 0 \data[15] [7:0] $end
$upscope $end
$upscope $end
$upscope $end
$upscope $end
$scope module CPUTest $end
$scope module cpu $end
$scope module data_path $end
$scope module data_memory $end
$var reg 8 1 \data[16] [7:0] $end
$upscope $end
$upscope $end
$upscope $end
$upscope $end
$scope module CPUTest $end
$scope module cpu $end
$scope module data_path $end
$scope module data_memory $end
$var reg 8 2 \data[17] [7:0] $end
$upscope $end
$upscope $end
$upscope $end
$upscope $end
$scope module CPUTest $end
$scope module cpu $end
$scope module data_path $end
$scope module data_memory $end
$var reg 8 3 \data[18] [7:0] $end
$upscope $end
$upscope $end
$upscope $end
$upscope $end
$scope module CPUTest $end
$scope module cpu $end
$scope module data_path $end
$scope module data_memory $end
$var reg 8 4 \data[19] [7:0] $end
$upscope $end
$upscope $end
$upscope $end
$upscope $end
$scope module CPUTest $end
$scope module cpu $end
$scope module data_path $end
$scope module stack $end
$var reg 8 5 \data[0] [7:0] $end
$upscope $end
$upscope $end
$upscope $end
$upscope $end
$scope module CPUTest $end
$scope module cpu $end
$scope module data_path $end
$scope module stack $end
$var reg 8 6 \data[1] [7:0] $end
$upscope $end
$upscope $end
$upscope $end
$upscope $end
$scope module CPUTest $end
$scope module cpu $end
$scope module data_path $end
$scope module stack $end
$var reg 8 7 \data[2] [7:0] $end
$upscope $end
$upscope $end
$upscope $end
$upscope $end
$scope module CPUTest $end
$scope module cpu $end
$scope module data_path $end
$scope module stack $end
$var reg 8 8 \data[3] [7:0] $end
$upscope $end
$upscope $end
$upscope $end
$upscope $end
$scope module CPUTest $end
$scope module cpu $end
$scope module data_path $end
$scope module stack $end
$var reg 8 9 \data[4] [7:0] $end
$upscope $end
$upscope $end
$upscope $end
$upscope $end
$scope module CPUTest $end
$scope module cpu $end
$scope module data_path $end
$scope module stack $end
$var reg 8 : \data[5] [7:0] $end
$upscope $end
$upscope $end
$upscope $end
$upscope $end
$scope module CPUTest $end
$scope module cpu $end
$scope module data_path $end
$scope module stack $end
$var reg 8 ; \data[6] [7:0] $end
$upscope $end
$upscope $end
$upscope $end
$upscope $end
$scope module CPUTest $end
$scope module cpu $end
$scope module data_path $end
$scope module stack $end
$var reg 8 < \data[7] [7:0] $end
$upscope $end
$upscope $end
$upscope $end
$upscope $end
$scope module CPUTest $end
$scope module cpu $end
$scope module data_path $end
$scope module stack $end
$var reg 8 = \data[8] [7:0] $end
$upscope $end
$upscope $end
$upscope $end
$upscope $end
$scope module CPUTest $end
$scope module cpu $end
$scope module data_path $end
$scope module stack $end
$var reg 8 > \data[9] [7:0] $end
$upscope $end
$upscope $end
$upscope $end
$upscope $end
$scope module CPUTest $end
$scope module cpu $end
$scope module data_path $end
$scope module stack $end
$var reg 8 ? \data[10] [7:0] $end
$upscope $end
$upscope $end
$upscope $end
$upscope $end
$scope module CPUTest $end
$scope module cpu $end
$scope module data_path $end
$scope module stack $end
$var reg 8 @ \data[11] [7:0] $end
$upscope $end
$upscope $end
$upscope $end
$upscope $end
$scope module CPUTest $end
$var reg 1 A clk $end
$scope module cpu $end
$var wire 2 B alu_op [1:0] $end
$var wire 1 C clk $end
$var wire 8 D inst [7:0] $end
$var wire 1 E ld_B $end
$var wire 1 F ld_IR $end
$var wire 1 G ld_MDR $end
$var wire 1 H ld_pc $end
$var wire 1 I mem_adr_src $end
$var wire 1 J mem_write_sig $end
$var wire 1 K pc_src $end
$var wire 1 L pop_sig $end
$var wire 1 M push_sig $end
$var wire 1 N stack_src $end
$var wire 1 O tos_sig $end
$var wire 1 P z $end
$scope module data_path $end
$var wire 2 Q alu_op [1:0] $end
$var wire 8 R alu_out [7:0] $end
$var wire 1 C clk $end
$var wire 8 S data_memory_out [7:0] $end
$var wire 1 E ld_B $end
$var wire 1 F ld_IR $end
$var wire 1 G ld_MDR $end
$var wire 1 H ld_pc $end
$var wire 1 I mem_adr_src $end
$var wire 1 J mem_write_sig $end
$var wire 1 K pc_src $end
$var wire 1 L pop_sig $end
$var wire 1 M push_sig $end
$var wire 8 T stack_out [7:0] $end
$var wire 1 N stack_src $end
$var wire 1 O tos_sig $end
$var reg 8 U B_reg [7:0] $end
$var reg 8 V alu_out_reg [7:0] $end
$var reg 8 W instruction [7:0] $end
$var reg 8 X mdr [7:0] $end
$var reg 5 Y pc [4:0] $end
$var reg 1 Z z $end
$scope module data_memory $end
$var wire 5 [ address [4:0] $end
$var wire 1 C clk $end
$var wire 1 J mem_write_sig $end
$var wire 8 \ write_data [7:0] $end
$var integer 32 ] i [31:0] $end
$var reg 8 ^ read_data [7:0] $end
$scope begin loop $end
$upscope $end
$upscope $end
$scope module stack $end
$var wire 1 C clk $end
$var wire 1 L pop_sig $end
$var wire 8 _ push_data [7:0] $end
$var wire 1 M push_sig $end
$var wire 1 O tos_sig $end
$var integer 32 ` i [31:0] $end
$var reg 8 a out_data [7:0] $end
$var reg 3 b stack_pointer [2:0] $end
$scope begin loop2 $end
$upscope $end
$upscope $end
$scope module alu $end
$var wire 8 c A [7:0] $end
$var wire 8 d B [7:0] $end
$var wire 2 e alu_op [1:0] $end
$var reg 8 f R [7:0] $end
$upscope $end
$upscope $end
$scope module controller $end
$var wire 1 C clk $end
$var wire 8 g inst [7:0] $end
$var wire 1 P zero $end
$var reg 2 h alu_op [1:0] $end
$var reg 1 i ld_B $end
$var reg 1 j ld_IR $end
$var reg 1 k ld_MDR $end
$var reg 1 l ld_pc $end
$var reg 1 m mem_adr_src $end
$var reg 1 n mem_write $end
$var reg 4 o ns [3:0] $end
$var reg 1 p pc_src $end
$var reg 4 q ps [3:0] $end
$var reg 1 r stack_pop $end
$var reg 1 s stack_push $end
$var reg 1 t stack_src $end
$var reg 1 u tos $end
$upscope $end
$upscope $end
$upscope $end
$enddefinitions $end
#0
$dumpvars
0u
0t
0s
0r
b1111 q
0p
b0 o
0n
0m
0l
0k
0j
0i
b0 h
bx g
bx f
b0 e
bx d
bx c
b0 b
bx a
b1100 `
bx _
bx ^
b10100 ]
bx \
bx [
xZ
b0 Y
bx X
bx W
bx V
bx U
bx T
bx S
bx R
b0 Q
xP
0O
0N
0M
0L
0K
0J
0I
0H
0G
0F
0E
bx D
0C
b0 B
0A
bx @
bx ?
bx >
bx =
bx <
bx ;
bx :
bx 9
bx 8
bx 7
bx 6
bx 5
bx 4
bx 3
b10 2
b1 1
b10101010 0
bx /
bx .
bx -
bx ,
bx +
bx *
bx )
bx (
bx '
b11111111 &
b0 %
b0 $
b10010001 #
b10010000 "
b10001111 !
$end
#20
b10001111 ^
b10001111 S
b0 [
1l
1H
1j
1F
1m
1I
b1 o
b0 q
1A
1C
#40
0A
0C
#60
1k
1G
b101 o
0j
0F
0m
0I
0l
0H
b10101010 ^
b10101010 S
b1111 [
b1 q
b10001111 W
b10001111 D
b10001111 g
b1 Y
1A
1C
#80
0A
0C
#100
1s
1M
b110 o
0k
0G
b10101010 _
b10101010 X
b101 q
1A
1C
#120
0A
0C
#140
b0 o
0s
0M
b110 q
0Z
0P
b10101010 a
b10101010 T
b10101010 \
b10101010 d
b1 b
b10101010 5
1A
1C
#160
0A
0C
#180
b10010000 ^
b10010000 S
b1 [
1l
1H
1j
1F
1m
1I
b1 o
b0 q
1A
1C
#200
0A
0C
#220
1k
1G
b101 o
0j
0F
0m
0I
0l
0H
b1 ^
b1 S
b10000 [
b1 q
b10010000 W
b10010000 D
b10010000 g
b10 Y
1A
1C
#240
0A
0C
#260
1s
1M
b110 o
0k
0G
b1 _
b1 X
b101 q
1A
1C
#280
0A
0C
#300
b0 o
0s
0M
b110 q
b1 a
b1 T
b1 \
b1 d
b10 b
b1 6
1A
1C
#320
0A
0C
#340
b10010001 ^
b10010001 S
b10 [
1l
1H
1j
1F
1m
1I
b1 o
b0 q
1A
1C
#360
0A
0C
#380
1k
1G
b101 o
0j
0F
0m
0I
0l
0H
b10 ^
b10 S
b10001 [
b1 q
b10010001 W
b10010001 D
b10010001 g
b11 Y
1A
1C
#400
0A
0C
#420
1s
1M
b110 o
0k
0G
b10 _
b10 X
b101 q
1A
1C
#440
0A
0C
#460
b0 o
0s
0M
b110 q
b10 a
b10 T
b10 \
b10 d
b11 b
b10 7
1A
1C
#480
0A
0C
#500
b0 ^
b0 S
b11 [
1l
1H
1j
1F
1m
1I
b1 o
b0 q
1A
1C
#520
0A
0C
#540
b10001111 ^
b10001111 S
1i
1E
1r
1L
b10 o
0j
0F
0m
0I
0l
0H
b0 [
b1 q
b0 W
b0 D
b0 g
b100 Y
1A
1C
#560
0A
0C
#580
1u
1O
b11 o
0i
0E
1r
1L
b100 f
b100 R
b10 U
b10 c
b10 q
b10 b
1A
1C
#600
0A
0C
#620
b11 _
1t
1N
1s
1M
b0 o
0r
0L
1u
1O
b11 q
b100 V
b11 f
b11 R
b1 b
b1 a
b1 T
b1 \
b1 d
1A
1C
#640
0A
0C
#660
b0 ^
b0 S
b100 [
1l
1H
1j
1F
1m
1I
b1 o
0s
0M
0u
0O
0t
0N
b11 V
b0 q
b10 _
b10101100 f
b10101100 R
b10 b
b11 6
b10101010 a
b10101010 T
b10101010 \
b10101010 d
1A
1C
#680
0A
0C
#700
1i
1E
1r
1L
b10 o
0j
0F
0m
0I
0l
0H
b10001111 ^
b10001111 S
b0 [
b1 q
b10101100 V
b101 Y
b101 f
b101 R
b11 a
b11 T
b11 \
b11 d
1A
1C
#720
0A
0C
#740
1u
1O
b11 o
0i
0E
1r
1L
b110 f
b110 R
b101 V
b11 U
b11 c
b10 q
b1 b
1A
1C
#760
0A
0C
#780
b10101101 _
1t
1N
1s
1M
b0 o
0r
0L
1u
1O
b11 q
b110 V
b10101101 f
b10101101 R
b0 b
b10101010 a
b10101010 T
b10101010 \
b10101010 d
1A
1C
#800
0A
0C
#820
b11111111 ^
b11111111 S
b101 [
1l
1H
1j
1F
1m
1I
b1 o
0s
0M
0u
0O
0t
0N
b10101101 V
b0 q
b10 _
bx f
bx R
b1 b
b10101101 5
bx a
bx T
bx \
bx d
1A
1C
#840
0A
0C
#860
b1010 o
0j
0F
0m
0I
0l
0H
bx ^
bx S
b11111 [
b1 q
bx V
b11111111 W
b11111111 D
b11111111 g
b110 Y
b10110000 f
b10110000 R
b10101101 a
b10101101 T
b10101101 \
b10101101 d
1A
1C
#880
0A
0C
#900
b10110000 V
1A
1C
